{
  "requirement_id": "r13",
  "from_version": "1",
  "to_version": "2",
  "changes": [
    {
      "change": "modify_data_values",
      "element": "action.data_values",
      "old": [
        {
          "element": "customer_outstanding_debt",
          "domain": [
            ">100"
          ],
          "format": "EUR"
        }
      ],
      "new": [
        {
          "element": "customer_outstanding_debt",
          "domain": [
            "[50.01,∞)"
          ]
        }
      ],
      "change_id": "r13_c1"
    }
  ]
}